fixed2csv.py
setup.py
fixed2csv.egg-info/PKG-INFO
fixed2csv.egg-info/SOURCES.txt
fixed2csv.egg-info/dependency_links.txt
fixed2csv.egg-info/not-zip-safe
fixed2csv.egg-info/requires.txt
fixed2csv.egg-info/top_level.txt