Metadata-Version: 1.1
Name: fixed2csv
Version: 0.2.4
Summary: Converts data files formatted in fixed-width columns to CSV.
Home-page: https://github.com/chrisspen/fixed2csv
Author: Chris Spencer
Author-email: chrisspen@gmail.com
License: LGPL
Platform: UNKNOWN
Classifier: Intended Audience :: Developers
Classifier: License :: OSI Approved :: GNU General Public License v3 (GPLv3)
Classifier: Operating System :: OS Independent
Classifier: Programming Language :: Python
